cmx4flex/__main__.py
cmx4flex/main.py
cmx4flex-0.5.0.dist-info/METADATA
cmx4flex-0.5.0.dist-info/WHEEL
cmx4flex-0.5.0.dist-info/entry_points.txt
cmx4flex-0.5.0.dist-info/top_level.txt
cmx4flex-0.5.0.dist-info/RECORD
